<?xml version="1.0" encoding="UTF-8"?>
<!DOCTYPE mapper PUBLIC "-//mybatis.org//DTD Mapper 3.0//EN" "http://mybatis.org/dtd/mybatis-3-mapper.dtd">
<mapper namespace="com.lswd.youpin.dao.lsyp.CanteenRecipeMapper">
  <resultMap id="BaseResultMap" type="com.lswd.youpin.model.lsyp.CanteenRecipe">
    <!--
      WARNING - @mbg.generated
      This element is automatically generated by MyBatis Generator, do not modify.
    -->
    <id column="id" jdbcType="INTEGER" property="id" />
    <result column="recipe_id" jdbcType="VARCHAR" property="recipeId" />
    <result column="update_user" jdbcType="VARCHAR" property="updateUser" />
    <result column="sale_time" jdbcType="TIMESTAMP" property="saleTime" />
    <result column="update_time" jdbcType="TIMESTAMP" property="updateTime" />
    <result column="safetyone" jdbcType="VARCHAR" property="safetyone" />
    <result column="safetytwo" jdbcType="VARCHAR" property="safetytwo" />
  </resultMap>
  <sql id="Base_Column_List">
    <!--
      WARNING - @mbg.generated
      This element is automatically generated by MyBatis Generator, do not modify.
    -->
    id, recipe_id, update_user, sale_time, update_time, safetyone, safetytwo
  </sql>
  <select id="selectByPrimaryKey" parameterType="java.lang.Integer" resultMap="BaseResultMap">
    <!--
      WARNING - @mbg.generated
      This element is automatically generated by MyBatis Generator, do not modify.
    -->
    select 
    <include refid="Base_Column_List" />
    from t_recipes_canteen
    where id = #{id,jdbcType=INTEGER}
  </select>
  <delete id="deleteByPrimaryKey" parameterType="java.lang.Integer">
    <!--
      WARNING - @mbg.generated
      This element is automatically generated by MyBatis Generator, do not modify.
    -->
    delete from t_recipes_canteen
    where id = #{id,jdbcType=INTEGER}
  </delete>
  <insert id="insert" parameterType="com.lswd.youpin.model.lsyp.CanteenRecipe">
    <!--
      WARNING - @mbg.generated
      This element is automatically generated by MyBatis Generator, do not modify.
    -->
    insert into t_recipes_canteen (id, recipe_id, update_user, 
      sale_time, update_time, safetyone, 
      safetytwo)
    values (#{id,jdbcType=INTEGER}, #{recipeId,jdbcType=VARCHAR}, #{updateUser,jdbcType=VARCHAR}, 
      #{saleTime,jdbcType=TIMESTAMP}, #{updateTime,jdbcType=TIMESTAMP}, #{safetyone,jdbcType=VARCHAR}, 
      #{safetytwo,jdbcType=VARCHAR})
  </insert>
  <insert id="insertSelective" parameterType="com.lswd.youpin.model.lsyp.CanteenRecipe">
    <!--
      WARNING - @mbg.generated
      This element is automatically generated by MyBatis Generator, do not modify.
    -->
    insert into t_recipes_canteen
    <trim prefix="(" suffix=")" suffixOverrides=",">
      <if test="id != null">
        id,
      </if>
      <if test="recipeId != null">
        recipe_id,
      </if>
      <if test="updateUser != null">
        update_user,
      </if>
      <if test="saleTime != null">
        sale_time,
      </if>
      <if test="updateTime != null">
        update_time,
      </if>
      <if test="safetyone != null">
        safetyone,
      </if>
      <if test="safetytwo != null">
        safetytwo,
      </if>
    </trim>
    <trim prefix="values (" suffix=")" suffixOverrides=",">
      <if test="id != null">
        #{id,jdbcType=INTEGER},
      </if>
      <if test="recipeId != null">
        #{recipeId,jdbcType=VARCHAR},
      </if>
      <if test="updateUser != null">
        #{updateUser,jdbcType=VARCHAR},
      </if>
      <if test="saleTime != null">
        #{saleTime,jdbcType=TIMESTAMP},
      </if>
      <if test="updateTime != null">
        #{updateTime,jdbcType=TIMESTAMP},
      </if>
      <if test="safetyone != null">
        #{safetyone,jdbcType=VARCHAR},
      </if>
      <if test="safetytwo != null">
        #{safetytwo,jdbcType=VARCHAR},
      </if>
    </trim>
  </insert>
  <update id="updateByPrimaryKeySelective" parameterType="com.lswd.youpin.model.lsyp.CanteenRecipe">
    <!--
      WARNING - @mbg.generated
      This element is automatically generated by MyBatis Generator, do not modify.
    -->
    update t_recipes_canteen
    <set>
      <if test="recipeId != null">
        recipe_id = #{recipeId,jdbcType=VARCHAR},
      </if>
      <if test="updateUser != null">
        update_user = #{updateUser,jdbcType=VARCHAR},
      </if>
      <if test="saleTime != null">
        sale_time = #{saleTime,jdbcType=TIMESTAMP},
      </if>
      <if test="updateTime != null">
        update_time = #{updateTime,jdbcType=TIMESTAMP},
      </if>
      <if test="safetyone != null">
        safetyone = #{safetyone,jdbcType=VARCHAR},
      </if>
      <if test="safetytwo != null">
        safetytwo = #{safetytwo,jdbcType=VARCHAR},
      </if>
    </set>
    where id = #{id,jdbcType=INTEGER}
  </update>
  <update id="updateByPrimaryKey" parameterType="com.lswd.youpin.model.lsyp.CanteenRecipe">
    <!--
      WARNING - @mbg.generated
      This element is automatically generated by MyBatis Generator, do not modify.
    -->
    update t_recipes_canteen
    set recipe_id = #{recipeId,jdbcType=VARCHAR},
      update_user = #{updateUser,jdbcType=VARCHAR},
      sale_time = #{saleTime,jdbcType=TIMESTAMP},
      update_time = #{updateTime,jdbcType=TIMESTAMP},
      safetyone = #{safetyone,jdbcType=VARCHAR},
      safetytwo = #{safetytwo,jdbcType=VARCHAR}
    where id = #{id,jdbcType=INTEGER}
  </update>
</mapper>